semvar/.req
semvar/__init__.py
semvar/console.py
semvar-1.2.0.dist-info/LICENSE.txt
semvar-1.2.0.dist-info/METADATA
semvar-1.2.0.dist-info/WHEEL
semvar-1.2.0.dist-info/entry_points.txt
semvar-1.2.0.dist-info/top_level.txt
semvar-1.2.0.dist-info/RECORD
