Metadata-Version: 2.1
Name: semvar
Version: 1.2.0
Summary: semvar
Home-page: UNKNOWN
Author: Ryumejin
Author-email: ryumejin@gmail.com
License: UNKNOWN
Platform: UNKNOWN
Requires-Dist: pyyaml
